plover_auto_identifier/__init__.py
plover_auto_identifier/controller.py
plover_auto_identifier-0.1.2.dist-info/LICENSE
plover_auto_identifier-0.1.2.dist-info/METADATA
plover_auto_identifier-0.1.2.dist-info/WHEEL
plover_auto_identifier-0.1.2.dist-info/entry_points.txt
plover_auto_identifier-0.1.2.dist-info/top_level.txt
plover_auto_identifier-0.1.2.dist-info/zip-safe
plover_auto_identifier-0.1.2.dist-info/RECORD
