Metadata-Version: 2.1
Name: plover-auto-identifier
Version: 0.1.2
Summary: Plover plugin to make typing identifier in programming languages easier
Home-page: https://github.com/user202729/plover_auto_identifier
Author: user202729
License: GNU General Public License v3 or later (GPLv3+)
Keywords: plover plover_plugin
Platform: UNKNOWN
Classifier: Environment :: Plugins
Classifier: License :: OSI Approved :: GNU General Public License v3 or later (GPLv3+)
Classifier: Operating System :: OS Independent
Classifier: Programming Language :: Python :: 3
Requires-Dist: plover (>=4.0.0.dev8)
